interpax/__init__.py
interpax/_coefs.py
interpax/_fd_derivs.py
interpax/_fourier.py
interpax/_ppoly.py
interpax/_spline.py
interpax/_version.py
interpax/py.typed
interpax/utils.py
interpax-0.3.12.dist-info/licenses/LICENSE
interpax-0.3.12.dist-info/METADATA
interpax-0.3.12.dist-info/WHEEL
interpax-0.3.12.dist-info/top_level.txt
interpax-0.3.12.dist-info/RECORD
